fabricator/__init__.py
fabricator/dataset_generator.py
fabricator/utils.py
fabricator/dataset_transformations/__init__.py
fabricator/dataset_transformations/question_answering.py
fabricator/dataset_transformations/text_classification.py
fabricator/dataset_transformations/token_classification.py
fabricator/prompts/__init__.py
fabricator/prompts/base.py
fabricator/prompts/utils.py
fabricator/samplers/__init__.py
fabricator/samplers/samplers.py
fabricator_ai-0.2.0.dist-info/LICENSE
fabricator_ai-0.2.0.dist-info/METADATA
fabricator_ai-0.2.0.dist-info/WHEEL
fabricator_ai-0.2.0.dist-info/top_level.txt
fabricator_ai-0.2.0.dist-info/RECORD
