Metadata-Version: 2.1
Name: fabricator-ai
Version: 0.2.0
Summary: Conveniently generating datasets with large language models.
Author: Humboldt University Berlin, deepset GmbH
Author-email: goldejon@informatik.hu-berlin.de
License: Apache 2.0
Requires-Python: >=3.8
License-File: LICENSE
Requires-Dist: datasets
Requires-Dist: farm-haystack >=1.18.0
Requires-Dist: loguru
